piglatinTeam7/__init__.py
piglatinTeam7/__main__.py
piglatinTeam7/pig.py
piglatinTeam7-1.0.3.dist-info/LICENSE
piglatinTeam7-1.0.3.dist-info/METADATA
piglatinTeam7-1.0.3.dist-info/WHEEL
piglatinTeam7-1.0.3.dist-info/entry_points.txt
piglatinTeam7-1.0.3.dist-info/top_level.txt
piglatinTeam7-1.0.3.dist-info/RECORD
