Metadata-Version: 2.1
Name: piglatinTeam7
Version: 1.0.3
Summary: This is a PigLatin Translator served with cute pigs
Author-email: team7 <wc1629@nyu.edu>
License: GNU GENERAL PUBLIC LICENSE
Project-URL: Homepage, https://github.com/software-students-fall2022/python-package-exercise-project-3-team-7
Project-URL: Repository, https://github.com/software-students-fall2022/python-package-exercise-project-3-team-7.git
Project-URL: Bug Tracker, https://github.com/software-students-fall2022/python-package-exercise-project-3-team-7/issues
Keywords: python,package,build,tutorial
Classifier: Programming Language :: Python :: 3
Classifier: Intended Audience :: Education
Classifier: License :: OSI Approved :: GNU General Public License v3 (GPLv3)
Classifier: Operating System :: OS Independent
Requires-Python: >=3.7
License-File: LICENSE
Provides-Extra: dev
Requires-Dist: pytest ; extra == 'dev'
